data/__init__.py
data/gtfo.json
pybins/__init__.py
pybins/functions.py
pybins/gtfo.py
pybins/linux.py
pybins/windows.py
pybins/data/__init__.py
pybins/data/db.json
pybins/data/gtfo.json
pybins-1.0.1.data/scripts/pybins
pybins-1.0.1.dist-info/LICENSE
pybins-1.0.1.dist-info/METADATA
pybins-1.0.1.dist-info/NOTICE
pybins-1.0.1.dist-info/WHEEL
pybins-1.0.1.dist-info/top_level.txt
pybins-1.0.1.dist-info/RECORD
