Metadata-Version: 2.1
Name: pybins
Version: 1.0.1
Summary: pybins is an command line utily that gather gtfobins and lolbins data.
Home-page: https://github.com/renatoalmeidaoliveira/pybins
Author: Renato Almeida de Oliveira
Author-email: renato.almeida.oliveira@gmail.com
License: UNKNOWN
Project-URL: Bug Tracker, https://github.com/renatoalmeidaoliveira/pybins/issues
Platform: UNKNOWN
Classifier: Programming Language :: Python :: 3
Classifier: License :: OSI Approved :: MIT License
Classifier: Operating System :: OS Independent
Requires-Python: >=3.6
License-File: LICENSE
License-File: NOTICE
Requires-Dist: colorama (>=0.4.4)
Requires-Dist: commonmark (>=0.9.1)
Requires-Dist: Pygments (>=2.9.0)
Requires-Dist: PyYAML (>=5.4.1)
Requires-Dist: rich (>=10.1.0)
Requires-Dist: tinydb (>=4.4.0)
Requires-Dist: typing-extensions (>=3.10.0.0)
